[
	{
		"name": "Ktube Media Downloader",
		"nickname": "ktube-media-downloader",
		"executable": "snap run ktube-media-downloader",
		"package": "ktube-media-downloader",
		"extra_packages": "",
		"architecture": "",
		"package_manager": "snap",
		"repository_name": "",
		"repository_cache": "",
		"repository_url": "",
		"icon_backg": "https://4.bp.blogspot.com/-2wslfX_v4YU/Xw0Pos4sEYI/AAAAAAAAYrw/6sIj1cnLMOkSAW97o_jfe4PQCWSkphzuACLcBGAsYHQ/s1600/ktube-backg.png",
		"price": "free",
		"dgpu": "deactivate"
    }
]
