[
	{
		"name": "Webcamoid",
		"nickname": "webcamoid",
		"executable": "webcamoid",
		"package": "webcamoid",
		"extra_packages": "",
		"architecture": "x86_64",
		"package_manager": "zypper",
		"repository_name": "",
		"repository_cache": "/var/cache/zypp/solv/multimedia-apps",
		"repository_url": "http://download.opensuse.org/repositories/multimedia:/apps/openSUSE_Leap_15.2/x86_64",
		"icon_backg": "https://2.bp.blogspot.com/-dgXrsd0Tz4c/WWK8ouXpV3I/AAAAAAAASIg/SaqAdffers4QUrHQLHt4bb_E9IP6_Ud-QCLcBGAs/s1600/webcamoid-backg.png",
		"price": "free",
		"dgpu": "deactivate"
	}
]
